lifejacket/__init__.py
lifejacket/arg_threading_helpers.py
lifejacket/calculate_derivatives.py
lifejacket/constants.py
lifejacket/deployment_conditioning_monitor.py
lifejacket/form_adjusted_meat_adjustments_directly.py
lifejacket/get_datum_for_blowup_supervised_learning.py
lifejacket/helper_functions.py
lifejacket/input_checks.py
lifejacket/post_deployment_analysis.py
lifejacket/small_sample_corrections.py
lifejacket/vmap_helpers.py
lifejacket-1.1.0.dist-info/METADATA
lifejacket-1.1.0.dist-info/WHEEL
lifejacket-1.1.0.dist-info/entry_points.txt
lifejacket-1.1.0.dist-info/top_level.txt
lifejacket-1.1.0.dist-info/RECORD
