Metadata-Version: 2.4
Name: lifejacket
Version: 1.1.0
Summary: Consistent standard errors for longitudinal data collected under pooling online decision policies.
Author-email: Nowell Closser <nowellclosser@gmail.com>
Requires-Python: >=3.10
Requires-Dist: click>=8.0
Requires-Dist: jax>=0.4.0
Requires-Dist: jaxlib>=0.4.0
Requires-Dist: numpy>=1.20.0
Requires-Dist: pandas>=1.3.0
Requires-Dist: scipy>=1.7.0
Requires-Dist: plotext>=5.0.0
Provides-Extra: dev
Requires-Dist: pytest>=7.0; extra == "dev"
Requires-Dist: black>=22.0; extra == "dev"
Requires-Dist: flake8>=4.0; extra == "dev"
